tootorch/__init__.py
tootorch/dataload.py
tootorch/main.py
tootorch/models.py
tootorch/utils.py
tootorch/visualization.py
tootorch/attention_methods/__init__.py
tootorch/attention_methods/cam.py
tootorch/attention_methods/cbam.py
tootorch/attention_methods/ran.py
tootorch/attention_methods/warn.py
tootorch/saliency/__init__.py
tootorch/saliency/attribution_methods.py
tootorch/saliency/ensembles.py
tootorch/saliency/evaluation_methods.py
tootourch/__init__.py
tootourch/dataload.py
tootourch/main.py
tootourch/models.py
tootourch/utils.py
tootourch/visualization.py
tootourch/attention_methods/__init__.py
tootourch/attention_methods/cam.py
tootourch/attention_methods/cbam.py
tootourch/attention_methods/ran.py
tootourch/attention_methods/warn.py
tootourch/saliency/__init__.py
tootourch/saliency/attribution_methods.py
tootourch/saliency/ensembles.py
tootourch/saliency/evaluation_methods.py
tootorch-0.2.dist-info/LICENSE
tootorch-0.2.dist-info/METADATA
tootorch-0.2.dist-info/WHEEL
tootorch-0.2.dist-info/top_level.txt
tootorch-0.2.dist-info/RECORD
