Metadata-Version: 2.1
Name: tootorch
Version: 0.2
Summary: Implemetation XAI in Computer Vision (Pytorch)
Home-page: https://github.com/TooTouch/tootorch
Author: Jaehuck Heo
Author-email: wogur379@gmail.com
License: UNKNOWN
Download-URL: https://github.com/TooTouch/tootorch/archive/v0.1.tar.gz
Keywords: tootorch,XAI
Platform: UNKNOWN
Classifier: Programming Language :: Python :: 3
Classifier: Programming Language :: Python :: 3.6
Classifier: Programming Language :: Python :: 3.7
Classifier: Topic :: Scientific/Engineering :: Artificial Intelligence
Classifier: Topic :: Software Development :: Libraries :: Python Modules
Requires-Python: >=3.6
Requires-Dist: torch
Requires-Dist: torchvision
Requires-Dist: h5py
Requires-Dist: tqdm
Requires-Dist: pillow
Requires-Dist: opencv-python
